Single_Cycle/src/CPU/ProgramCounter.v


module ProgramCounter(

    input wire clk,
    input wire[63:0] Src1,

    input wire PcWrite,
    input wire halt,
    input wire reset,

    output wire[63:0] PC_output

);


wire [63:0]Src0;
reg  [63:0]CurrentProgramCounter;

assign Src0 = CurrentProgramCounter + 4;



// PC needs to be changed
always @(posedge clk or posedge reset) begin
    
    if( reset ) begin
       CurrentProgramCounter <= 0; 
    end
    else if( PcWrite == 1 ) begin

        CurrentProgramCounter <= Src1;
    end
    else if( halt == 1) begin
        CurrentProgramCounter <= CurrentProgramCounter;
    end
    else begin
    
        CurrentProgramCounter <= Src0;

    end

end

assign PC_output = CurrentProgramCounter;

endmodule

Single_Cycle/src/TestBenches/ProgramCounter/ProgramCounter_tb.v
`timescale 1ns/1ns

module ProgramCounter_tb;



reg clk;
reg halt;
reg reset;
reg [63:0]Src1;
reg PcWrite;

wire[63:0] PC_output;

integer cases_passed;
integer cases_ran;

integer i=0;
integer caseHalt = 1;
integer caseReset = 1;
integer caseCount = 1;


ProgramCounter PC(.clk(clk) ,
                  .Src1(Src1),
                  .PcWrite(PcWrite),
                  .halt(halt),
                  .reset(reset),
                  .PC_output(PC_output));

initial begin
     clk = 0;
end

always #5 clk = ~clk;


initial begin
    $dumpfile("./TestBenches/ProgramCounter/ProgramCounter.vcd");
    $dumpvars(0 , ProgramCounter_tb );



    // Init

    cases_passed = 0;
    cases_ran = 0;

    Src1 = 0;

    PcWrite = 0;
    reset = 1;
    halt = 0;



    // test 1 program counter iteration
    #1;
    reset = 0;

    $display("Beginning counting case");
    @(posedge clk); #1;
    for( i = 1; i < 10; i = i + 1) begin
    
        if( PC_output != i * 4) begin
        
            caseCount = 0;
        end
        @(posedge clk); #1;
    end

    cases_ran = cases_ran + 1;

    #1

    // Test 2 rest Case
    $display("Beginning reset case");

    reset = 1;

    #1

    if( PC_output != 0 ) begin
    
        caseReset = 0;
    
    end 

    reset = 0;
    cases_ran = cases_ran + 1;

    #1;
    // Test 3 Halt case

    halt = 1;
    i = 0;
    $display("Beginning halt case");
    @(posedge clk); #1;
    for( i = 0; i < 5; i = i + 1) begin
        
        if( PC_output != 0) begin
            caseHalt = 0;
        end
        @(posedge clk); #1;
    end

    cases_ran = cases_ran + 1;
    
    $display("----------RESULTS----------");
    
    if ( caseCount) begin
        $display("Count case passed");
        cases_passed = cases_passed + 1;
    end
    else begin
        $display("Count case failed");
    end

    if ( caseHalt ) begin
        $display("Halt case passed");
        cases_passed = cases_passed + 1;
    end
    else begin
        $display("Halt case failed" , cases_ran);
    end

    if ( caseReset ) begin
        $display("Reset Case passed");
        cases_passed = cases_passed + 1;
    end
    else begin
        $display("Reset Case failed");
    end

    $finish;
end

endmodule

Single_Cycle/src/TestBenches/ProgramCounter/ProgramCounter.vcd
$date
	Wed Aug 12 22:31:02 2026
$end
$version
	Icarus Verilog
$end
$timescale
	1ns
$end
$scope module ProgramCounter_tb $end
$var wire 64 ! PC_output [63:0] $end
$var reg 1 " PcWrite $end
$var reg 64 # Src1 [63:0] $end
$var reg 1 $ clk $end
$var reg 1 % halt $end
$var reg 1 & reset $end
$var integer 32 ' caseCount [31:0] $end
$var integer 32 ( caseHalt [31:0] $end
$var integer 32 ) caseReset [31:0] $end
$var integer 32 * cases_passed [31:0] $end
$var integer 32 + cases_ran [31:0] $end
$var integer 32 , i [31:0] $end
$scope module PC $end
$var wire 64 - PC_output [63:0] $end
$var wire 1 " PcWrite $end
$var wire 64 . Src1 [63:0] $end
$var wire 1 $ clk $end
$var wire 1 % halt $end
$var wire 1 & reset $end
$var wire 64 / Src0 [63:0] $end
$var reg 64 0 CurrentProgramCounter [63:0] $end
$upscope $end
$upscope $end
$enddefinitions $end
$comment Show the parameter values. $end
$dumpall
$end
#0
$dumpvars
b0 0
b100 /
b0 .
b0 -
b0 ,
b0 +
b0 *
b1 )
b1 (
b1 '
1&
0%
0$
b0 #
0"
b0 !
$end
#1
0&
#5
b1000 /
b100 !
b100 -
b100 0
1$
#6
b1 ,
#10
0$
#15
b1100 /
b1000 !
b1000 -
b1000 0
1$
#16
b10 ,
#20
0$
#25
b10000 /
b1100 !
b1100 -
b1100 0
1$
#26
b11 ,
#30
0$
#35
b10100 /
b10000 !
b10000 -
b10000 0
1$
#36
b100 ,
#40
0$
#45
b11000 /
b10100 !
b10100 -
b10100 0
1$
#46
b101 ,
#50
0$
#55
b11100 /
b11000 !
b11000 -
b11000 0
1$
#56
b110 ,
#60
0$
#65
b100000 /
b11100 !
b11100 -
b11100 0
1$
#66
b111 ,
#70
0$
#75
b100100 /
b100000 !
b100000 -
b100000 0
1$
#76
b1000 ,
#80
0$
#85
b101000 /
b100100 !
b100100 -
b100100 0
1$
#86
b1001 ,
#90
0$
#95
b101100 /
b101000 !
b101000 -
b101000 0
1$
#96
b1 +
b1010 ,
#97
b100 /
b0 !
b0 -
b0 0
1&
#98
b10 +
0&
#99
b0 ,
1%
#100
0$
#105
1$
#110
0$
#115
1$
#116
b1 ,
#120
0$
#125
1$
#126
b10 ,
#130
0$
#135
1$
#136
b11 ,
#140
0$
#145
1$
#146
b100 ,
#150
0$
#155
1$
#156
b11 *
b11 +
b101 ,
