Single_Cycle/src/CPU/Basic_ALU.v


module Basic_ALU(

    input wire clk,
    input wire[4:0] OpCode,
    input wire[31:0] data1,
    input wire[31:0] data2, 

    output wire[31:0] ALU_output

);

reg [31:0] tempout;

always @(*) begin

    case( OpCode )

        0  : tempout <= $signed(data1) + $signed(data2);       // ADD
        2  : tempout <= $signed(data1) - $signed(data2);       // SUB
        3  : tempout <= data1 << data2[4:0];                   // SLL
        5  : tempout <= $signed(data1) < $signed(data2);       // SLT
        6  : tempout <= data1 ^ data2;                         // XOR
        8  : tempout <= data1 >> data2[4:0];                   // SRL
        9  : tempout <= $signed(data1) >>> data2[4:0];         // SRA
        10 : tempout <= data1 | data2;                         // OR
        12 : tempout <= data1 & data2;                         // AND
        13 : tempout <= data2 << 12;                           // LUI
        default : tempout <= 0; 
    endcase

end

assign ALU_output = $unsigned(tempout);

endmodule

Single_Cycle/src/TestBenches/ALU/Basic_ALU_tb.v
`timescale 1ns/1ns


module Basic_ALU_tb;

reg clk;

reg [4:0]OpCode;
reg [31:0]data1;
reg [31:0]data2;


wire [31:0]ALU_output;

Basic_ALU ALU(  .clk(clk),
                .OpCode(OpCode),
                .data1(data1),
                .data2(data2),
                .ALU_output(ALU_output)
                );

initial begin 
    clk = 0;
end;

always #5 clk = ~clk;


initial begin

    $dumpfile("./TestBenches/ALU/Basic_ALU.vcd");
    $dumpvars(0 , Basic_ALU_tb );


    data1 = 0;
    data2 = 0;
    OpCode = 0;

    #1
    //ADD
    data1 = 32'hFFFFFFFF;
    data2 = 1;

    #1;
    //SUB
    OpCode = 2;
    data1 = 32'hFFFF0000;
    data2 = 32'hFFFF0000;

    #1
    //SLL
    OpCode = 3;
    data1 = 1; 
    data2 = 8;

    #1
    //SLT
    OpCode = 5;
    data1 = 32'hFFFFFFFF;
    data2 = 32'h00000000;
    #1
    //XOR
    OpCode = 6;
    data1 = 32'hF0F0F0F0;
    data2 = 32'h0F0F0F0F;

    #1
    //SRL
    OpCode = 8;
    data1 = 32'h80000000;
    data2 = 4;
    #1
    //SRA
    OpCode = 9;
    data1 = 32'h80000000;
    data2 = 4;

    #1
    //OR
    OpCode = 10;
    data1 = 32'hFFFF0000;
    data2 = 32'h0000FFFF;

    #1
    //AND
    OpCode = 12;
    data1 = 32'hFFFFF000;
    data2 = 32'h0000FFFF;

    #1
    //LUI
    OpCode = 13;
    data2 = 32'h0000BEEF;



    $finish;



end






endmodule

Single_Cycle/src/TestBenches/ALU/Basic_ALU.vcd
$date
	Wed Aug 12 22:31:56 2026
$end
$version
	Icarus Verilog
$end
$timescale
	1ns
$end
$scope module Basic_ALU_tb $end
$var wire 32 ! ALU_output [31:0] $end
$var reg 5 " OpCode [4:0] $end
$var reg 1 # clk $end
$var reg 32 $ data1 [31:0] $end
$var reg 32 % data2 [31:0] $end
$scope module ALU $end
$var wire 5 & OpCode [4:0] $end
$var wire 1 # clk $end
$var wire 32 ' data1 [31:0] $end
$var wire 32 ( data2 [31:0] $end
$var wire 32 ) ALU_output [31:0] $end
$var reg 32 * tempout [31:0] $end
$upscope $end
$upscope $end
$enddefinitions $end
$comment Show the parameter values. $end
$dumpall
$end
#0
$dumpvars
b0 *
b0 )
b0 (
b0 '
b0 &
b0 %
b0 $
0#
b0 "
b0 !
$end
#1
b1 %
b1 (
b11111111111111111111111111111111 $
b11111111111111111111111111111111 '
#2
b11111111111111110000000000000000 %
b11111111111111110000000000000000 (
b11111111111111110000000000000000 $
b11111111111111110000000000000000 '
b10 "
b10 &
#3
b100000000 !
b100000000 )
b100000000 *
b1000 %
b1000 (
b1 $
b1 '
b11 "
b11 &
#4
b1 !
b1 )
b1 *
b0 %
b0 (
b11111111111111111111111111111111 $
b11111111111111111111111111111111 '
b101 "
b101 &
#5
b11111111111111111111111111111111 !
b11111111111111111111111111111111 )
b11111111111111111111111111111111 *
b1111000011110000111100001111 %
b1111000011110000111100001111 (
b11110000111100001111000011110000 $
b11110000111100001111000011110000 '
b110 "
b110 &
1#
#6
b1000000000000000000000000000 !
b1000000000000000000000000000 )
b1000000000000000000000000000 *
b100 %
b100 (
b10000000000000000000000000000000 $
b10000000000000000000000000000000 '
b1000 "
b1000 &
#7
b11111000000000000000000000000000 !
b11111000000000000000000000000000 )
b11111000000000000000000000000000 *
b1001 "
b1001 &
#8
b11111111111111111111111111111111 !
b11111111111111111111111111111111 )
b11111111111111111111111111111111 *
b1111111111111111 %
b1111111111111111 (
b11111111111111110000000000000000 $
b11111111111111110000000000000000 '
b1010 "
b1010 &
#9
b1111000000000000 !
b1111000000000000 )
b1111000000000000 *
b11111111111111111111000000000000 $
b11111111111111111111000000000000 '
b1100 "
b1100 &
#10
b1011111011101111000000000000 !
b1011111011101111000000000000 )
b1011111011101111000000000000 *
b1011111011101111 %
b1011111011101111 (
b1101 "
b1101 &
0#
