Single_Cycle/src/CPU/RegFile.v

module RegFile(
    input wire clk,
    input wire enable,
    input wire write_en,
    input wire reset,

    input wire [4:0] read_addr,
    input wire [4:0] write_addr,

    input wire [31:0] data_in,
    output wire [31:0] data_out
);


reg [31:0] regs[31:0];
integer i = 0;

always @(posedge clk && enable or posedge reset) begin
    if( reset ) begin
        for( i = 0; i < 32 ; i++) begin
            regs[i] <= 0;
        end
    end
    else if ( write_en ) begin
    
        regs[write_addr] <= data_in;

    end
end


assign  data_out = regs[read_addr];



endmodule

Single_Cycle/src/TestBenches/RegFile/RegFile_tb.v
`timescale 1ns/1ns


module RegFile_tb;

integer cases_passed;
integer cases_ran;

integer passed = 1;

wire [31:0]data_out;

reg clk;

reg write_en;
reg read_en;
reg reset;
reg [4:0]read_addr;
reg [4:0]write_addr;
reg [31:0]data_in;
reg enable;

wire [31:0] r0, r1, r2, r3, r4, r5, r6, r7;
wire [31:0] r8, r9, r10, r11, r12, r13, r14, r15;
wire [31:0] r16, r17, r18, r19, r20, r21, r22, r23;
wire [31:0] r24, r25, r26, r27, r28, r29, r30, r31;


RegFile regfile(.clk(clk),
             .write_en(write_en),
             .reset(reset),
             .read_addr(read_addr),
             .write_addr(write_addr),
             .data_in(data_in),
             .enable(enable),
             .data_out(data_out));


assign r0  = regfile.regs[0];
assign r1  = regfile.regs[1];
assign r2  = regfile.regs[2];
assign r3  = regfile.regs[3];
assign r4  = regfile.regs[4];
assign r5  = regfile.regs[5];
assign r6  = regfile.regs[6];
assign r7  = regfile.regs[7];
assign r8  = regfile.regs[8];
assign r9  = regfile.regs[9];
assign r10 = regfile.regs[10];
assign r11 = regfile.regs[11];
assign r12 = regfile.regs[12];
assign r13 = regfile.regs[13];
assign r14 = regfile.regs[14];
assign r15 = regfile.regs[15];
assign r16 = regfile.regs[16];
assign r17 = regfile.regs[17];
assign r18 = regfile.regs[18];
assign r19 = regfile.regs[19];
assign r20 = regfile.regs[20];
assign r21 = regfile.regs[21];
assign r22 = regfile.regs[22];
assign r23 = regfile.regs[23];
assign r24 = regfile.regs[24];
assign r25 = regfile.regs[25];
assign r26 = regfile.regs[26];
assign r27 = regfile.regs[27];
assign r28 = regfile.regs[28];
assign r29 = regfile.regs[29];
assign r30 = regfile.regs[30];
assign r31 = regfile.regs[31];

integer i;

initial begin
clk = 0;
end

always #5 clk = ~clk;

initial begin
    $dumpfile("./TestBenches/RegFile/RegFile.vcd");
    $dumpvars(0 , RegFile_tb );
        

    // INIT

    cases_passed = 0;
    cases_ran = 0;

    reset = 1;
    data_in = 0;
    write_addr = 0;
    read_addr = 0;
    write_en = 0;
    read_en = 0;
    enable = 0;


    #1
    reset = 0;
    #1

    enable = 1;

    // CASE 1 Write to register r31
    $display("Case, Write to registers" , cases_ran);
    for(i = 0; i < 32; i = i + 1) begin 
    
        write_en = 1;
        write_addr = i;
        data_in =  32'hFFFFFFFF;

        @(posedge clk); #1;

        write_en = 0;
        write_addr = 0;
        data_in = 0;

        #1;
    
    end

    // Checking case 
    i = 0;
    write_addr = 0;
    write_en = 0;

    for( i = 0; i < 32; i = i + 1) begin
    
        read_addr = i;

        if( data_out != 32'hFFFFFFFF ) begin
            passed = 0;
        end

    end

    if ( passed ) begin
        $display("Case %d: passed" , cases_ran);
        cases_passed = cases_passed + 1;
    end
    else begin
        $display("Case %d: failed" , cases_ran);
    end

    cases_ran = cases_ran + 1;

    $display("----------RESULTS----------");
    $display("Cases Ran:    %d" , cases_ran);
    $display("Cases Passed: %d" , cases_passed);
    $display("Cases Failed: %d" , cases_ran - cases_passed);
    $finish;
end

endmodule

Single_Cycle/src/TestBenches/RegFile/RegFile.vcd
$date
	Wed Aug 12 22:30:22 2026
$end
$version
	Icarus Verilog
$end
$timescale
	1ns
$end
$scope module RegFile_tb $end
$var wire 32 ! r0 [31:0] $end
$var wire 32 " r1 [31:0] $end
$var wire 32 # r10 [31:0] $end
$var wire 32 $ r11 [31:0] $end
$var wire 32 % r12 [31:0] $end
$var wire 32 & r13 [31:0] $end
$var wire 32 ' r14 [31:0] $end
$var wire 32 ( r15 [31:0] $end
$var wire 32 ) r16 [31:0] $end
$var wire 32 * r17 [31:0] $end
$var wire 32 + r18 [31:0] $end
$var wire 32 , r19 [31:0] $end
$var wire 32 - r2 [31:0] $end
$var wire 32 . r20 [31:0] $end
$var wire 32 / r21 [31:0] $end
$var wire 32 0 r22 [31:0] $end
$var wire 32 1 r23 [31:0] $end
$var wire 32 2 r24 [31:0] $end
$var wire 32 3 r25 [31:0] $end
$var wire 32 4 r26 [31:0] $end
$var wire 32 5 r27 [31:0] $end
$var wire 32 6 r28 [31:0] $end
$var wire 32 7 r29 [31:0] $end
$var wire 32 8 r3 [31:0] $end
$var wire 32 9 r30 [31:0] $end
$var wire 32 : r31 [31:0] $end
$var wire 32 ; r4 [31:0] $end
$var wire 32 < r5 [31:0] $end
$var wire 32 = r6 [31:0] $end
$var wire 32 > r7 [31:0] $end
$var wire 32 ? r8 [31:0] $end
$var wire 32 @ r9 [31:0] $end
$var wire 32 A data_out [31:0] $end
$var reg 1 B clk $end
$var reg 32 C data_in [31:0] $end
$var reg 1 D enable $end
$var reg 5 E read_addr [4:0] $end
$var reg 1 F read_en $end
$var reg 1 G reset $end
$var reg 5 H write_addr [4:0] $end
$var reg 1 I write_en $end
$var integer 32 J cases_passed [31:0] $end
$var integer 32 K cases_ran [31:0] $end
$var integer 32 L i [31:0] $end
$var integer 32 M passed [31:0] $end
$scope module regfile $end
$var wire 1 B clk $end
$var wire 32 N data_in [31:0] $end
$var wire 32 O data_out [31:0] $end
$var wire 1 D enable $end
$var wire 5 P read_addr [4:0] $end
$var wire 1 G reset $end
$var wire 5 Q write_addr [4:0] $end
$var wire 1 I write_en $end
$var integer 32 R i [31:0] $end
$upscope $end
$upscope $end
$enddefinitions $end
$comment Show the parameter values. $end
$dumpall
$end
#0
$dumpvars
b100000 R
b0 Q
b0 P
b0 O
b0 N
b1 M
bx L
b0 K
b0 J
0I
b0 H
1G
0F
b0 E
0D
b0 C
0B
b0 A
b0 @
b0 ?
b0 >
b0 =
b0 <
b0 ;
b0 :
b0 9
b0 8
b0 7
b0 6
b0 5
b0 4
b0 3
b0 2
b0 1
b0 0
b0 /
b0 .
b0 -
b0 ,
b0 +
b0 *
b0 )
b0 (
b0 '
b0 &
b0 %
b0 $
b0 #
b0 "
b0 !
$end
#1
0G
#2
b11111111111111111111111111111111 C
b11111111111111111111111111111111 N
1I
b0 L
1D
#5
b11111111111111111111111111111111 A
b11111111111111111111111111111111 O
b11111111111111111111111111111111 !
1B
#6
b0 C
b0 N
0I
#7
b11111111111111111111111111111111 C
b11111111111111111111111111111111 N
b1 H
b1 Q
1I
b1 L
#10
0B
#15
b11111111111111111111111111111111 "
1B
#16
b0 C
b0 N
b0 H
b0 Q
0I
#17
b11111111111111111111111111111111 C
b11111111111111111111111111111111 N
b10 H
b10 Q
1I
b10 L
#20
0B
#25
b11111111111111111111111111111111 -
1B
#26
b0 C
b0 N
b0 H
b0 Q
0I
#27
b11111111111111111111111111111111 C
b11111111111111111111111111111111 N
b11 H
b11 Q
1I
b11 L
#30
0B
#35
b11111111111111111111111111111111 8
1B
#36
b0 C
b0 N
b0 H
b0 Q
0I
#37
b11111111111111111111111111111111 C
b11111111111111111111111111111111 N
b100 H
b100 Q
1I
b100 L
#40
0B
#45
b11111111111111111111111111111111 ;
1B
#46
b0 C
b0 N
b0 H
b0 Q
0I
#47
b11111111111111111111111111111111 C
b11111111111111111111111111111111 N
b101 H
b101 Q
1I
b101 L
#50
0B
#55
b11111111111111111111111111111111 <
1B
#56
b0 C
b0 N
b0 H
b0 Q
0I
#57
b11111111111111111111111111111111 C
b11111111111111111111111111111111 N
b110 H
b110 Q
1I
b110 L
#60
0B
#65
b11111111111111111111111111111111 =
1B
#66
b0 C
b0 N
b0 H
b0 Q
0I
#67
b11111111111111111111111111111111 C
b11111111111111111111111111111111 N
b111 H
b111 Q
1I
b111 L
#70
0B
#75
b11111111111111111111111111111111 >
1B
#76
b0 C
b0 N
b0 H
b0 Q
0I
#77
b11111111111111111111111111111111 C
b11111111111111111111111111111111 N
b1000 H
b1000 Q
1I
b1000 L
#80
0B
#85
b11111111111111111111111111111111 ?
1B
#86
b0 C
b0 N
b0 H
b0 Q
0I
#87
b11111111111111111111111111111111 C
b11111111111111111111111111111111 N
b1001 H
b1001 Q
1I
b1001 L
#90
0B
#95
b11111111111111111111111111111111 @
1B
#96
b0 C
b0 N
b0 H
b0 Q
0I
#97
b11111111111111111111111111111111 C
b11111111111111111111111111111111 N
b1010 H
b1010 Q
1I
b1010 L
#100
0B
#105
b11111111111111111111111111111111 #
1B
#106
b0 C
b0 N
b0 H
b0 Q
0I
#107
b11111111111111111111111111111111 C
b11111111111111111111111111111111 N
b1011 H
b1011 Q
1I
b1011 L
#110
0B
#115
b11111111111111111111111111111111 $
1B
#116
b0 C
b0 N
b0 H
b0 Q
0I
#117
b11111111111111111111111111111111 C
b11111111111111111111111111111111 N
b1100 H
b1100 Q
1I
b1100 L
#120
0B
#125
b11111111111111111111111111111111 %
1B
#126
b0 C
b0 N
b0 H
b0 Q
0I
#127
b11111111111111111111111111111111 C
b11111111111111111111111111111111 N
b1101 H
b1101 Q
1I
b1101 L
#130
0B
#135
b11111111111111111111111111111111 &
1B
#136
b0 C
b0 N
b0 H
b0 Q
0I
#137
b11111111111111111111111111111111 C
b11111111111111111111111111111111 N
b1110 H
b1110 Q
1I
b1110 L
#140
0B
#145
b11111111111111111111111111111111 '
1B
#146
b0 C
b0 N
b0 H
b0 Q
0I
#147
b11111111111111111111111111111111 C
b11111111111111111111111111111111 N
b1111 H
b1111 Q
1I
b1111 L
#150
0B
#155
b11111111111111111111111111111111 (
1B
#156
b0 C
b0 N
b0 H
b0 Q
0I
#157
b11111111111111111111111111111111 C
b11111111111111111111111111111111 N
b10000 H
b10000 Q
1I
b10000 L
#160
0B
#165
b11111111111111111111111111111111 )
1B
#166
b0 C
b0 N
b0 H
b0 Q
0I
#167
b11111111111111111111111111111111 C
b11111111111111111111111111111111 N
b10001 H
b10001 Q
1I
b10001 L
#170
0B
#175
b11111111111111111111111111111111 *
1B
#176
b0 C
b0 N
b0 H
b0 Q
0I
#177
b11111111111111111111111111111111 C
b11111111111111111111111111111111 N
b10010 H
b10010 Q
1I
b10010 L
#180
0B
#185
b11111111111111111111111111111111 +
1B
#186
b0 C
b0 N
b0 H
b0 Q
0I
#187
b11111111111111111111111111111111 C
b11111111111111111111111111111111 N
b10011 H
b10011 Q
1I
b10011 L
#190
0B
#195
b11111111111111111111111111111111 ,
1B
#196
b0 C
b0 N
b0 H
b0 Q
0I
#197
b11111111111111111111111111111111 C
b11111111111111111111111111111111 N
b10100 H
b10100 Q
1I
b10100 L
#200
0B
#205
b11111111111111111111111111111111 .
1B
#206
b0 C
b0 N
b0 H
b0 Q
0I
#207
b11111111111111111111111111111111 C
b11111111111111111111111111111111 N
b10101 H
b10101 Q
1I
b10101 L
#210
0B
#215
b11111111111111111111111111111111 /
1B
#216
b0 C
b0 N
b0 H
b0 Q
0I
#217
b11111111111111111111111111111111 C
b11111111111111111111111111111111 N
b10110 H
b10110 Q
1I
b10110 L
#220
0B
#225
b11111111111111111111111111111111 0
1B
#226
b0 C
b0 N
b0 H
b0 Q
0I
#227
b11111111111111111111111111111111 C
b11111111111111111111111111111111 N
b10111 H
b10111 Q
1I
b10111 L
#230
0B
#235
b11111111111111111111111111111111 1
1B
#236
b0 C
b0 N
b0 H
b0 Q
0I
#237
b11111111111111111111111111111111 C
b11111111111111111111111111111111 N
b11000 H
b11000 Q
1I
b11000 L
#240
0B
#245
b11111111111111111111111111111111 2
1B
#246
b0 C
b0 N
b0 H
b0 Q
0I
#247
b11111111111111111111111111111111 C
b11111111111111111111111111111111 N
b11001 H
b11001 Q
1I
b11001 L
#250
0B
#255
b11111111111111111111111111111111 3
1B
#256
b0 C
b0 N
b0 H
b0 Q
0I
#257
b11111111111111111111111111111111 C
b11111111111111111111111111111111 N
b11010 H
b11010 Q
1I
b11010 L
#260
0B
#265
b11111111111111111111111111111111 4
1B
#266
b0 C
b0 N
b0 H
b0 Q
0I
#267
b11111111111111111111111111111111 C
b11111111111111111111111111111111 N
b11011 H
b11011 Q
1I
b11011 L
#270
0B
#275
b11111111111111111111111111111111 5
1B
#276
b0 C
b0 N
b0 H
b0 Q
0I
#277
b11111111111111111111111111111111 C
b11111111111111111111111111111111 N
b11100 H
b11100 Q
1I
b11100 L
#280
0B
#285
b11111111111111111111111111111111 6
1B
#286
b0 C
b0 N
b0 H
b0 Q
0I
#287
b11111111111111111111111111111111 C
b11111111111111111111111111111111 N
b11101 H
b11101 Q
1I
b11101 L
#290
0B
#295
b11111111111111111111111111111111 7
1B
#296
b0 C
b0 N
b0 H
b0 Q
0I
#297
b11111111111111111111111111111111 C
b11111111111111111111111111111111 N
b11110 H
b11110 Q
1I
b11110 L
#300
0B
#305
b11111111111111111111111111111111 9
1B
#306
b0 C
b0 N
b0 H
b0 Q
0I
#307
b11111111111111111111111111111111 C
b11111111111111111111111111111111 N
b11111 H
b11111 Q
1I
b11111 L
#310
0B
#315
b11111111111111111111111111111111 :
1B
#316
b0 C
b0 N
b0 H
b0 Q
0I
#317
b1 K
b1 J
b11111 E
b11111 P
b100000 L
